ddata/__init__.py
ddata/date.py
ddata/loggor.py
ddata/pandas.py
ddata/test.py
ddata-0.2.2.dist-info/METADATA
ddata-0.2.2.dist-info/WHEEL
ddata-0.2.2.dist-info/entry_points.txt
ddata-0.2.2.dist-info/top_level.txt
ddata-0.2.2.dist-info/RECORD
