Metadata-Version: 2.1
Name: ddata
Version: 0.2.2
Summary: A Python data package
Home-page: https://github.com/flyphant/ddata
Author: flyphant
Author-email: 576938286@qq.com
License: UNKNOWN
Keywords: python,package,sample
Platform: UNKNOWN
Classifier: Programming Language :: Python :: 3
Classifier: License :: OSI Approved :: MIT License
Classifier: Operating System :: OS Independent
Requires-Python: >=3.6, <4
Requires-Dist: numpy
Provides-Extra: dev
Requires-Dist: pytest>=3.7; extra == "dev"
